femtodriver/ENV_REQUIREMENTS.sh
femtodriver/PY_REQUIREMENTS
femtodriver/VERSION
femtodriver/__init__.py
femtodriver/addr_map_spu1p3.py
femtodriver/addr_map_spu2p0.py
femtodriver/cfg.py
femtodriver/fd_dataclasses.py
femtodriver/femtodrive.py
femtodriver/fqir_runner.py
femtodriver/fx_runner.py
femtodriver/program_handler.py
femtodriver/pull_femtocrux_image.py
femtodriver/spu_runner.py
femtodriver/typing_help.py
femtodriver/plugins/__init__.py
femtodriver/plugins/evk2_plugin.py
femtodriver/plugins/fake_redis_client.py
femtodriver/plugins/femtofile_export.py
femtodriver/plugins/io_plugin.py
femtodriver/plugins/redis_plugin.py
femtodriver/plugins/zynq_plugin.py
femtodriver/resources/clara8ms_2-1-L-eargowdrc.femto
femtodriver/resources/identity.femto
femtodriver/resources/identity.pt
femtodriver/util/__init__.py
femtodriver/util/binfile.py
femtodriver/util/fake_socket.py
femtodriver/util/hexfile.py
femtodriver/util/packing.py
femtodriver/util/print_header.py
femtodriver/util/run_util.py
femtodriver-1.8.4.dist-info/licenses/LICENSE
femtodriver-1.8.4.dist-info/METADATA
femtodriver-1.8.4.dist-info/WHEEL
femtodriver-1.8.4.dist-info/entry_points.txt
femtodriver-1.8.4.dist-info/top_level.txt
femtodriver-1.8.4.dist-info/RECORD
